ckanext_chat-0.1.6a0-py3.13-nspkg.pth
ckanext/chat/__init__.py
ckanext/chat/action.py
ckanext/chat/auth.py
ckanext/chat/helpers.py
ckanext/chat/plugin.py
ckanext/chat/views.py
ckanext/chat/assets/katex.min.css
ckanext/chat/assets/katex.min.js
ckanext/chat/assets/script.js
ckanext/chat/assets/style.css
ckanext/chat/assets/webassets.yml
ckanext/chat/i18n/de/LC_MESSAGES/ckanext-chat.mo
ckanext/chat/public/.gitignore
ckanext/chat/public/static/katex/fonts/KaTeX_AMS-Regular.ttf
ckanext/chat/public/static/katex/fonts/KaTeX_AMS-Regular.woff
ckanext/chat/public/static/katex/fonts/KaTeX_AMS-Regular.woff2
ckanext/chat/public/static/katex/fonts/KaTeX_Caligraphic-Bold.ttf
ckanext/chat/public/static/katex/fonts/KaTeX_Caligraphic-Bold.woff
ckanext/chat/public/static/katex/fonts/KaTeX_Caligraphic-Bold.woff2
ckanext/chat/public/static/katex/fonts/KaTeX_Caligraphic-Regular.ttf
ckanext/chat/public/static/katex/fonts/KaTeX_Caligraphic-Regular.woff
ckanext/chat/public/static/katex/fonts/KaTeX_Caligraphic-Regular.woff2
ckanext/chat/public/static/katex/fonts/KaTeX_Fraktur-Bold.ttf
ckanext/chat/public/static/katex/fonts/KaTeX_Fraktur-Bold.woff
ckanext/chat/public/static/katex/fonts/KaTeX_Fraktur-Bold.woff2
ckanext/chat/public/static/katex/fonts/KaTeX_Fraktur-Regular.ttf
ckanext/chat/public/static/katex/fonts/KaTeX_Fraktur-Regular.woff
ckanext/chat/public/static/katex/fonts/KaTeX_Fraktur-Regular.woff2
ckanext/chat/public/static/katex/fonts/KaTeX_Main-Bold.ttf
ckanext/chat/public/static/katex/fonts/KaTeX_Main-Bold.woff
ckanext/chat/public/static/katex/fonts/KaTeX_Main-Bold.woff2
ckanext/chat/public/static/katex/fonts/KaTeX_Main-BoldItalic.ttf
ckanext/chat/public/static/katex/fonts/KaTeX_Main-BoldItalic.woff
ckanext/chat/public/static/katex/fonts/KaTeX_Main-BoldItalic.woff2
ckanext/chat/public/static/katex/fonts/KaTeX_Main-Italic.ttf
ckanext/chat/public/static/katex/fonts/KaTeX_Main-Italic.woff
ckanext/chat/public/static/katex/fonts/KaTeX_Main-Italic.woff2
ckanext_chat-0.1.6a0.dist-info/METADATA
ckanext_chat-0.1.6a0.dist-info/WHEEL
ckanext_chat-0.1.6a0.dist-info/entry_points.txt
ckanext_chat-0.1.6a0.dist-info/namespace_packages.txt
ckanext_chat-0.1.6a0.dist-info/top_level.txt
ckanext_chat-0.1.6a0.dist-info/RECORD
