Metadata-Version: 2.4
Name: ckanext-chat
Version: 0.1.6a0
Summary: Extension adds a pydantic ai chat interface to CKAN, that can run actions with user aware context.
Home-page: https://github.com/Mat-O-Lab/ckanext-chat
Author: Thomas Hanke
Author-email: thomas.hanke@iwm.fraunhofer.de
License: AGPL
Requires-Dist: pydantic-ai-slim[logfire,openai]>=0.3.1
Requires-Dist: openai
Requires-Dist: logfire[httpx]
Requires-Dist: nest_asyncio
Requires-Dist: pymilvus==2.5.5
Requires-Dist: tiktoken
Requires-Dist: regex
Requires-Dist: aiofiles
Requires-Dist: aiohttp[speedups]
Requires-Dist: loguru
Dynamic: author
Dynamic: author-email
Dynamic: description
Dynamic: description-content-type
Dynamic: home-page
Dynamic: license
Dynamic: requires-dist
Dynamic: summary
